kobo_highlights/__init__.py
kobo_highlights/config.py
kobo_highlights/console.py
kobo_highlights/functions.py
kobo_highlights/main.py
kobo_highlights-1.0.5.dist-info/LICENSE
kobo_highlights-1.0.5.dist-info/METADATA
kobo_highlights-1.0.5.dist-info/WHEEL
kobo_highlights-1.0.5.dist-info/entry_points.txt
kobo_highlights-1.0.5.dist-info/RECORD
