Metadata-Version: 2.3
Name: kobo-highlights
Version: 1.0.5
Summary: Kobo Highlights is a CLI application to manage the bookmarks of your Kobo ereader. It can import them into a human-friendly markdown database.
License: GPL-3.0-only
Author: Pedro Videgain Barranco
Author-email: pedro@vide.bar
Requires-Python: ~=3.10
Classifier: Environment :: Console
Classifier: Operating System :: POSIX :: Linux
Classifier: Topic :: Multimedia
Requires-Dist: pydantic (>=2.0,<3.0)
Requires-Dist: rich (>=12.4.0,<12.5.0)
Requires-Dist: toml (>=0.10.2,<0.11.0)
Requires-Dist: typer[all] (>=0.15.4,<0.16.0)
